MANIFEST.in
README.txt
actions-0.c
actions-1.c
actions-2.c
actions-3.c
actions-4.c
actions-5.c
actions-6.c
actions.h
config.h
guestfs-stringlists-utils.h
guestfs.py
handle.c
module.c
setup.py
stringlists-utils.c
structs.c
pyguestfs.egg-info/PKG-INFO
pyguestfs.egg-info/SOURCES.txt
pyguestfs.egg-info/dependency_links.txt
pyguestfs.egg-info/top_level.txt